djedi_jinja.py
djedi_cms_jinja2-2.0.3.dist-info/DESCRIPTION.rst
djedi_cms_jinja2-2.0.3.dist-info/METADATA
djedi_cms_jinja2-2.0.3.dist-info/RECORD
djedi_cms_jinja2-2.0.3.dist-info/WHEEL
djedi_cms_jinja2-2.0.3.dist-info/metadata.json
djedi_cms_jinja2-2.0.3.dist-info/top_level.txt
