Metadata-Version: 2.0
Name: djedi-cms-jinja2
Version: 2.0.3
Summary: Jinja variants of the Djedi template tags.
Home-page: UNKNOWN
Author: Christopher Rosell
Author-email: chrippa@tanuki.se
License: BSD
Platform: UNKNOWN
Requires-Dist: djedi-cms
Requires-Dist: jinja2
